capnp/__init__.pxd
capnp/__init__.py
capnp/_gen.py
capnp/c++.capnp
capnp/schema.capnp
capnp/version.py
capnp/helpers/__init__.pxd
capnp/helpers/asyncHelper.h
capnp/helpers/asyncIoHelper.h
capnp/helpers/capabilityHelper.h
capnp/helpers/checkCompiler.h
capnp/helpers/fixMaybe.h
capnp/helpers/helpers.pxd
capnp/helpers/non_circular.pxd
capnp/helpers/rpcHelper.h
capnp/helpers/serialize.h
capnp/includes/__init__.pxd
capnp/includes/capnp_cpp.pxd
capnp/includes/schema_cpp.pxd
capnp/includes/types.pxd
capnp/lib/__init__.pxd
capnp/lib/__init__.py
capnp/lib/capnp.cpython-37m-darwin.so
capnp/lib/capnp.pxd
capnp/lib/capnp.pyx
capnp/lib/pickle_helper.py
capnp/templates/module.pyx
capnp/templates/setup.py.tmpl
pycapnp_async-0.7.0.dist-info/LICENSE
pycapnp_async-0.7.0.dist-info/METADATA
pycapnp_async-0.7.0.dist-info/WHEEL
pycapnp_async-0.7.0.dist-info/entry_points.txt
pycapnp_async-0.7.0.dist-info/top_level.txt
pycapnp_async-0.7.0.dist-info/RECORD
